dimopy/__init__.py
dimopy/business/__init__.py
dimopy/business/derive_data.py
dimopy/business/synthetic_data.py
dimopy/common/__init__.py
dimopy/common/utils.py
dimopy/common/data_preprocessing/__init__.py
dimopy/common/data_preprocessing/data_filling.py
dimopy/common/data_preprocessing/data_load.py
dimopy/common/data_preprocessing/data_normalization.py
dimopy/common/data_preprocessing/data_outliers.py
dimopy/common/data_preprocessing/data_periods.py
dimopy/common/data_preprocessing/data_process.py
dimopy/common/data_preprocessing/data_smoothing.py
dimopy/core/__init__.py
dimopy/core/api.py
dimopy/core/common.py
dimopy/datasets/__init__.py
dimopy/datasets/dataloader.py
dimopy/datasets/splitter.py
dimopy/datasets/tsdataset.py
dimopy/datasets/repository/__init__.py
dimopy/datasets/repository/base.py
dimopy/datasets/repository/datasets_config.py
dimopy/error/__init__.py
dimopy/error/catch.py
dimopy/error/response.py
dimopy/logger/__init__.py
dimopy/logger/logger.py
dimopy/models/__init__.py
dimopy/models/anomaly/Ksigma.py
dimopy/models/anomaly/__init__.py
dimopy/models/anomaly/anomaly_transformer.py
dimopy/models/anomaly/auto_encoder.py
dimopy/models/anomaly/auto_encoder_torch.py
dimopy/models/anomaly/base.py
dimopy/models/anomaly/base_dl.py
dimopy/models/anomaly/box_plot.py
dimopy/models/anomaly/cof.py
dimopy/models/anomaly/ewma.py
dimopy/models/anomaly/hbos.py
dimopy/models/anomaly/iforest.py
dimopy/models/anomaly/kde.py
dimopy/models/anomaly/knn.py
dimopy/models/anomaly/lof.py
dimopy/models/anomaly/ocsvm.py
dimopy/models/anomaly/pca.py
dimopy/models/anomaly/sos.py
dimopy/models/anomaly/vae.py
dimopy/models/anomaly/xgbod.py
dimopy/models/anomaly/lib/__init__.py
dimopy/models/anomaly/lib/attn.py
dimopy/models/anomaly/lib/embed.py
dimopy/models/anomaly/lib/encoder.py
dimopy/models/anomaly/lib/utils/__init__.py
dimopy/models/anomaly/lib/utils/logger.py
dimopy/models/anomaly/lib/utils/stat_models.py
dimopy/models/anomaly/lib/utils/torch_utility.py
dimopy-0.0.1.dist-info/LICENSE
dimopy-0.0.1.dist-info/METADATA
dimopy-0.0.1.dist-info/WHEEL
dimopy-0.0.1.dist-info/top_level.txt
dimopy-0.0.1.dist-info/RECORD
